IncidentResponse/__init__.py
IncidentResponse/main.py
IncidentResponse-0.0.1.dist-info/LICENSE
IncidentResponse-0.0.1.dist-info/METADATA
IncidentResponse-0.0.1.dist-info/WHEEL
IncidentResponse-0.0.1.dist-info/top_level.txt
IncidentResponse-0.0.1.dist-info/RECORD
