Metadata-Version: 2.1
Name: IncidentResponse
Version: 0.0.1
Summary: The IncidentResponse package streamlines the post-breach process, offering tools for data analysis, extraction, and notification management.
Author: Ranjeet Aloriya
Author-email: ranjeet.aloriya@gmail.com
Keywords: breach response,breach notification,notification lists,data consolidation,unique identifiers,affected parties,data merging,efficiency tools,duplicate notifications incident response,document review,data consolidation,unique identifiers,affected parties,data merging,efficiency tools,duplicate notifications,incident response,breach response
Classifier: Programming Language :: Python :: 3
Classifier: License :: OSI Approved :: MIT License
Classifier: Operating System :: OS Independent
Classifier: Development Status :: 5 - Production/Stable
Classifier: Intended Audience :: Developers
Classifier: Topic :: Software Development :: Libraries :: Python Modules
Classifier: Natural Language :: English
Classifier: Environment :: Console
Requires-Python: >=3.6
License-File: LICENSE
Requires-Dist: pandas
Requires-Dist: scipy
Requires-Dist: numpy
Requires-Dist: polars
Requires-Dist: jupyter
Requires-Dist: matplotlib
Requires-Dist: scikit-learn
Requires-Dist: xgboost
Requires-Dist: tensorflow
Requires-Dist: tensorboard
